{
  "id": "00000000-0000-0000-0000-000000000000",
  "appSettings": [],
  "bagItProfiles": [
    {
      "id": "386dbd66-598b-46e2-85ea-745729b3ed42",
      "name": "GinkoNet",
      "description": "GinkoNet Unique Profile for Consistent Deposit to Distributed Digital Preservation Services (BTR)",
      "acceptBagItVersion": [
        "0.97",
        "1.0"
      ],
      "acceptSerialization": [
        "application/tar"
      ],
      "allowFetchTxt": false,
      "bagItProfileInfo": {
        "bagItProfileIdentifier": "{clay will supply later}",
        "bagItProfileVersion": "1.3.0",
        "contactEmail": "axp1175@case.edu",
        "contactName": "GinkoNet Workflow Working Group",
        "externalDescription": "GinkoNet Unique Profile for Consistent Deposit to Distributed Digital Preservation Services (BTR)",
        "sourceOrganization": "GinkoNet",
        "version": "0.1"
      },
      "manifestsRequired": [
        "sha256"
      ],
      "manifestsAllowed": [
        "md5",
        "sha1",
        "sha224",
        "sha256",
        "sha384",
        "sha512"
      ],
      "tagManifestsRequired": [
        "sha256"
      ],
      "tagManifestsAllowed": [
        "md5",
        "sha1",
        "sha224",
        "sha256",
        "sha384",
        "sha512"
      ],
      "tagFilesAllowed": [
        "*"
      ],
      "tags": [
        {
          "id": "fa8c1c97-e441-45a4-a403-0056a913e024",
          "tagFile": "bagit.txt",
          "tagName": "BagIt-Version",
          "required": true,
          "values": [
            "0.97",
            "1.0"
          ],
          "defaultValue": "1.0",
          "userValue": "",
          "help": "Which version of the BagIt specification describes this bag's format?",
          "isBuiltIn": false,
          "isUserAddedFile": false,
          "isUserAddedTag": false,
          "wasAddedForJob": false
        },
        {
          "id": "f6e6e503-2ca4-4be0-8a75-61736f36bd0d",
          "tagFile": "bagit.txt",
          "tagName": "Tag-File-Character-Encoding",
          "required": true,
          "values": [],
          "defaultValue": "UTF-8",
          "userValue": "",
          "help": "How are this bag's plain-text tag files encoded? (Hint: usually UTF-8)",
          "isBuiltIn": false,
          "isUserAddedFile": false,
          "isUserAddedTag": false,
          "wasAddedForJob": false
        },
        {
          "id": "189b5fbe-1fb0-409f-9a60-b2ae4a1afcdb",
          "tagFile": "bag-info.txt",
          "tagName": "Source-Organization",
          "required": true,
          "values": [
            "Case Western Reserve University",
            "Indiana University",
            "InDiPres",
            "Purdue University",
            "University of Louisville",
            "Notre Dame"
          ],
          "defaultValue": "",
          "userValue": "",
          "help": "GinkoNet Member organization transferring the content",
          "isBuiltIn": false,
          "isUserAddedFile": false,
          "isUserAddedTag": false,
          "wasAddedForJob": false
        },
        {
          "id": "49d93738-c8d9-443e-b991-2cdc675e2215",
          "tagFile": "bag-info.txt",
          "tagName": "Bag-Count",
          "required": false,
          "values": [],
          "defaultValue": "",
          "userValue": "",
          "help": "Suggested Use: Sequential Number for Multiple Bag Collection and total number of Bags in the collection, formatted X of Y  (ex. 1 of 10)",
          "isBuiltIn": false,
          "isUserAddedFile": false,
          "isUserAddedTag": false,
          "wasAddedForJob": false
        },
        {
          "id": "7ced5b62-d40d-46d2-8e9a-8f3226427db6",
          "tagFile": "bag-info.txt",
          "tagName": "Bag-Group-Identifier",
          "required": false,
          "values": [],
          "defaultValue": "",
          "userValue": "",
          "help": "Suggested Use: Collection Identifier or Name",
          "isBuiltIn": false,
          "isUserAddedFile": false,
          "isUserAddedTag": false,
          "wasAddedForJob": false
        },
        {
          "id": "b100ad16-70bc-4ad1-9c98-01e4137356cb",
          "tagFile": "bag-info.txt",
          "tagName": "Bag-Size",
          "required": false,
          "values": [],
          "defaultValue": null,
          "userValue": "",
          "help": "",
          "isBuiltIn": false,
          "isUserAddedFile": false,
          "isUserAddedTag": false,
          "wasAddedForJob": false
        },
        {
          "id": "97aec582-d404-4491-97ea-e98a022bca56",
          "tagFile": "bag-info.txt",
          "tagName": "Bagging-Date",
          "required": true,
          "values": [],
          "defaultValue": null,
          "userValue": "",
          "help": "",
          "isBuiltIn": false,
          "isUserAddedFile": false,
          "isUserAddedTag": false,
          "wasAddedForJob": false
        },
        {
          "id": "0c4f8130-d4dd-42a9-874c-75c15015df04",
          "tagFile": "bag-info.txt",
          "tagName": "Bagging-Software",
          "required": false,
          "values": [],
          "defaultValue": null,
          "userValue": "",
          "help": "",
          "isBuiltIn": false,
          "isUserAddedFile": false,
          "isUserAddedTag": false,
          "wasAddedForJob": false
        },
        {
          "id": "cfa3d099-59d5-4683-8157-0dbb1041230b",
          "tagFile": "bag-info.txt",
          "tagName": "Depositor-Name",
          "required": true,
          "values": [],
          "defaultValue": "",
          "userValue": "",
          "help": "Required Use: Individual at the source organization who is depositing the bag",
          "isBuiltIn": false,
          "isUserAddedFile": false,
          "isUserAddedTag": false,
          "wasAddedForJob": false
        },
        {
          "id": "87d235bd-f737-4832-aedd-f0372b767383",
          "tagFile": "bag-info.txt",
          "tagName": "External-Description",
          "required": false,
          "values": [],
          "defaultValue": "",
          "userValue": "",
          "help": "Recommended Use: A brief explanation of the contents and provenance",
          "isBuiltIn": false,
          "isUserAddedFile": false,
          "isUserAddedTag": false,
          "wasAddedForJob": false
        },
        {
          "id": "7e309443-3fbb-445e-b9e0-baee41543427",
          "tagFile": "bag-info.txt",
          "tagName": "External-Identifier",
          "required": false,
          "values": [],
          "defaultValue": "",
          "userValue": "",
          "help": "Recommended Use: A sender-supplied identifier for the bag",
          "isBuiltIn": false,
          "isUserAddedFile": false,
          "isUserAddedTag": false,
          "wasAddedForJob": false
        },
        {
          "id": "3036dcd5-4154-4935-b7b8-c935505842f3",
          "tagFile": "bag-info.txt",
          "tagName": "Internal-Description",
          "required": false,
          "values": [],
          "defaultValue": "",
          "userValue": "",
          "help": "Suggested Use: A sender-local explanation of the contents and provenance",
          "isBuiltIn": false,
          "isUserAddedFile": false,
          "isUserAddedTag": false,
          "wasAddedForJob": false
        },
        {
          "id": "cacf92ef-a91e-4ec0-91e4-f8699d9489f6",
          "tagFile": "bag-info.txt",
          "tagName": "Internal-Identifier",
          "required": false,
          "values": [],
          "defaultValue": "",
          "userValue": "",
          "help": "Suggested Use: An alternate sender-specific identifier for the content and/or bag",
          "isBuiltIn": false,
          "isUserAddedFile": false,
          "isUserAddedTag": false,
          "wasAddedForJob": false
        },
        {
          "id": "7c4bcb13-5080-47f9-924b-38f13f3945aa",
          "tagFile": "bag-info.txt",
          "tagName": "Payload-Oxum",
          "required": true,
          "values": [],
          "defaultValue": null,
          "userValue": "",
          "help": "",
          "isBuiltIn": false,
          "isUserAddedFile": false,
          "isUserAddedTag": false,
          "wasAddedForJob": false
        },
        {
          "id": "ae807498-34af-4330-80f6-498bbf9b5963",
          "tagFile": "bag-info.txt",
          "tagName": "Notes",
          "required": false,
          "values": [],
          "defaultValue": "",
          "userValue": "",
          "help": "",
          "isBuiltIn": false,
          "isUserAddedFile": false,
          "isUserAddedTag": true,
          "wasAddedForJob": false
        }
      ],
      "serialization": "required",
      "baseProfileId": null,
      "isBuiltIn": false,
      "tarDirMustMatchName": false
    }
  ],
  "questions": [],
  "remoteRepositories": [],
  "storageServices": []
}